{
  "uid": "PIONANR5L17B2570",
  "titre": "Transmettre au Parlement les avis du Conseil d’État sur les projets de loi",
  "date_depot": "2026-03-03",
  "categorie": "Institutions et démocratie",
  "link": "https://www.assemblee-nationale.fr/dyn/opendata/PIONANR5L17B2570.html",
  "accroche": "Cette loi organique impose la transmission des avis du Conseil d'État sur les projets de loi au Parlement, garantissant plus de transparence.",
  "points": [
    "Modifie la loi organique (loi d'organisation des pouvoirs) de 2009 pour ajouter une obligation de transmission d'avis.",
    "Exige que les avis du Conseil d'État soient déposés au Parlement en même temps que les projets de loi concernés.",
    "Empêche le Gouvernement de choisir de ne pas rendre publics certains avis du Conseil d'État sur les projets de loi.",
    "Ne s'applique pas aux projets de loi concernant les traités internationaux, afin de ne pas gêner la diplomatie."
  ],
  "quality_score": null,
  "quality_flags": [],
  "dossier_uid": "DLR5L17N53879",
  "etat": "En cours",
  "statut": "1ère lecture en commission",
  "depositaire": "Florent Boudié (EPR)"
}