{
  "uid": "PIONANR5L17B2478",
  "titre": "Création d'un CHU en Corse",
  "date_depot": "2026-02-12",
  "categorie": "Santé",
  "link": "https://www.assemblee-nationale.fr/dyn/opendata/PIONANR5L17B2478.html",
  "accroche": "Cette proposition de loi rend obligatoire la présence d'au moins un Centre Hospitalier Universitaire (CHU) dans chaque région française, y compris en Corse.",
  "points": [
    "Modifie le code de la santé publique pour y inclure de nouvelles dispositions sur les centres hospitaliers.",
    "Exige que chaque région dispose désormais d'au minimum un centre hospitalier universitaire sur son territoire.",
    "Définit l'entrée en vigueur de cette nouvelle obligation légale au 1er janvier 2031.",
    "Prévoit une suppression de cette règle pour certains territoires spécifiques visés par l'article L. 6414-2."
  ],
  "quality_score": null,
  "quality_flags": [],
  "dossier_uid": "DLR5L17N50604",
  "etat": "En cours",
  "statut": "1ère lecture en séance publique",
  "depositaire": null
}