{
  "uid": "PIONANR5L17B2928",
  "titre": "Droits voisins de la presse",
  "date_depot": "2026-06-17",
  "categorie": "Numérique",
  "link": "https://www.assemblee-nationale.fr/dyn/opendata/PIONANR5L17B2928.html",
  "accroche": "La loi renforce les droits des éditeurs de presse et agences face aux plateformes numériques pour la juste rémunération de leurs contenus.",
  "points": [
    "Oblige les services en ligne à fournir aux éditeurs de presse des informations détaillées sur l'utilisation de leurs publications.",
    "Permet à l'ARCOM de fixer le montant de la rémunération due par les plateformes aux éditeurs de presse.",
    "Autorise l'ARCOM à prononcer des sanctions financières jusqu'à 1% du chiffre d'affaires mondial en cas de non-respect.",
    "Étend les pouvoirs d'enquête de l'ARCOM, incluant la collecte automatisée de données publiques sur les plateformes."
  ],
  "quality_score": 100,
  "quality_flags": [],
  "dossier_uid": "DLR5L17N51330",
  "etat": "En cours",
  "statut": "2ème lecture en commission",
  "depositaire": null
}