{
  "uid": "PIONANR5L17B2387",
  "titre": "Instaurer une contribution des personnes détenues condamnés aux frais d’incarcération",
  "date_depot": "2026-01-27",
  "categorie": "Justice et sécurité",
  "link": "https://www.assemblee-nationale.fr/dyn/opendata/PIONANR5L17B2387.html",
  "accroche": "Les personnes condamnées et détenues pourraient bientôt contribuer financièrement à une partie de leurs frais d'incarcération, à un taux fixe.",
  "points": [
    "Instaure une contribution obligatoire pour les personnes définitivement condamnées, afin de couvrir une partie des frais d'incarcération.",
    "Applique cette contribution sur les sommes disponibles du compte des détenus, y compris l'argent gagné en prison.",
    "Exclut de cette contribution les mineurs, les prévenus, les personnes sans ressources et celles en maison d'arrêt.",
    "Fixe le taux de la contribution à 5 % de chaque montant perçu par le détenu sur son compte disponible."
  ],
  "quality_score": null,
  "quality_flags": [],
  "dossier_uid": "DLR5L17N53674",
  "etat": "Déposé",
  "statut": "Texte déposé",
  "depositaire": "Christophe Naegelen (LIOT)"
}