{
  "uid": "PIONANR5L17BTC2520",
  "titre": "Renforcer la place des agriculteurs dans l’aménagement du territoire et à sécuriser l’exercice des activités agricoles face au changement climatique",
  "date_depot": "2026-02-24",
  "categorie": "Économie et travail",
  "link": "https://www.assemblee-nationale.fr/dyn/opendata/PIONANR5L17BTC2520.html",
  "accroche": "Cette proposition de loi renforcerait le rôle des agriculteurs dans l'aménagement du territoire et aiderait à sécuriser leurs activités face au changement climatique.",
  "points": [
    "Impliquerait des organismes de défense des produits agricoles dans les décisions d'aménagement du territoire.",
    "Obligerait les chambres d'agriculture à signaler les projets menaçant les productions agricoles sous signe de qualité.",
    "Considérerait les activités agricoles adaptant leurs horaires aux aléas climatiques comme normalement continues.",
    "Modifierait des articles du code de l'urbanisme et du code rural et de la pêche maritime."
  ],
  "quality_score": null,
  "quality_flags": [],
  "dossier_uid": "DLR5L17N53715",
  "etat": "En cours",
  "statut": "1ère lecture en séance publique",
  "depositaire": "Hubert Ott (Dem)"
}